aspxstats/__init__.py
aspxstats/async_client.py
aspxstats/client.py
aspxstats/exceptions.py
aspxstats/parsing.py
aspxstats/schema.py
aspxstats/types.py
aspxstats/validation.py
aspxstats/bf2/__init__.py
aspxstats/bf2/async_client.py
aspxstats/bf2/async_fetch.py
aspxstats/bf2/client.py
aspxstats/bf2/fetch.py
aspxstats/bf2/schemas.py
aspxstats/bf2/types.py
aspxstats/bf2/utils.py
aspxstats-0.5.1.dist-info/licenses/LICENSE
aspxstats-0.5.1.dist-info/METADATA
aspxstats-0.5.1.dist-info/WHEEL
aspxstats-0.5.1.dist-info/top_level.txt
aspxstats-0.5.1.dist-info/RECORD
